CHANGELOG
MANIFEST.in
README.rst
porter.py
setup.py
porter.egg-info/PKG-INFO
porter.egg-info/SOURCES.txt
porter.egg-info/dependency_links.txt
porter.egg-info/top_level.txt