Metadata-Version: 1.0
Name: porter
Version: 0.1.5
Summary: Porter: Simple File Operations in Python
Home-page: https://github.com/shunfan/porter
Author: Shunfan Du
Author-email: i@perry.asia
License: MIT
Keywords: file directory operation tool
Platform: UNKNOWN
Classifier: Development Status :: 2 - Pre-Alpha
Classifier: Intended Audience :: Developers
Classifier: License :: OSI Approved :: MIT License
Classifier: Programming Language :: Python :: 2.7
Classifier: Programming Language :: Python :: 3.2
Classifier: Programming Language :: Python :: 3.3
Classifier: Topic :: Software Development :: Build Tools
Classifier: Topic :: System :: Filesystems
Classifier: Topic :: Utilities
